aalec/__init__.pyi
aalec/beeper.pyi
aalec/button.pyi
aalec/display.pyi
aalec/encoder.pyi
aalec/environment.pyi
aalec/rgb_strip.pyi
aalec/constants/__init__.pyi
aalec/constants/beeper.pyi
aalec/constants/button.pyi
aalec/constants/display.pyi
aalec/constants/environment.pyi
aalec/constants/general.pyi
aalec/constants/rgb_strip.pyi
aalec/third_party/__init__.pyi
aalec/third_party/bmp280.pyi
aalec/third_party/sh1106.pyi
aalec_micropython_stubs-0.3.6.dist-info/METADATA
aalec_micropython_stubs-0.3.6.dist-info/WHEEL
aalec_micropython_stubs-0.3.6.dist-info/RECORD
