Metadata-Version: 2.4
Name: aalec-micropython-stubs
Version: 0.3.6
Summary: Stubs for Micropython Firmware for the AALeC
Project-URL: Homepage, https://github.com/informatik-aalen/aalec-micropython
Project-URL: Documentation, https://informatik-aalen.github.io/aalec-micropython
Project-URL: Repository, https://github.com/informatik-aalen/aalec-micropython
Project-URL: Issues, https://github.com/informatik-aalen/aalec-micropython/issues
Author-email: Sebastian Stigler <sebastian.stigler@hs-aalen.de>
Classifier: Development Status :: 5 - Production/Stable
Classifier: Natural Language :: English
Classifier: Operating System :: OS Independent
Classifier: Programming Language :: Python
Classifier: Programming Language :: Python :: 3
Classifier: Programming Language :: Python :: 3 :: Only
Classifier: Programming Language :: Python :: Implementation :: MicroPython
Classifier: Topic :: Software Development :: Documentation
Classifier: Topic :: Software Development :: Embedded Systems
Classifier: Topic :: Software Development :: Testing
Classifier: Topic :: Text Editors :: Integrated Development Environments (IDE)
Classifier: Typing :: Stubs Only
Requires-Python: >=3.10
Requires-Dist: esptool>=4.8.1
Requires-Dist: micropython-esp8266-stubs>=1.23.0.post2
Requires-Dist: mpremote>=1.25.0
